{
  "apiVersion": "enterprises.upmc.com/v1",
  "kind": "ElasticsearchCluster",
  "metadata": {
    "name": "example-es-cluster"
  },
  "spec": {
    "cluster-name": "primary",
    "zones": ["us-east-1c", "us-east-1d", "us-east-1e"],
    "node-specs":{
        "master":{
            "replicas": 2
        },
        "client": {
            "replicas": 3
        },
        "data": {
            "replicas": 3,
            "cpu-req": "1000m",
            "mem-req": "2Gi",
            "heap-max": 1800
        }
    },
    "data-volume-size": "10Gi",
    "snapshot": {
      "scheduler-enabled": true,
      "bucket-name": "elasticsnapshots99",
      "cron-schedule": "@every 2m"
    },
    "storage": {
      "type": "gp2",
      "storage-class-provisioner": "kubernetes.io/aws-ebs"
    }
  }
}
